ii_tools/__init__.py
ii_tools-0.1.dist-info/DESCRIPTION.rst
ii_tools-0.1.dist-info/LICENSE.txt
ii_tools-0.1.dist-info/METADATA
ii_tools-0.1.dist-info/RECORD
ii_tools-0.1.dist-info/WHEEL
ii_tools-0.1.dist-info/metadata.json
ii_tools-0.1.dist-info/top_level.txt
