Metadata-Version: 2.0
Name: ii-tools
Version: 0.1
Summary: ideallical tools
Home-page: https://github.com/ideallical/ii_tools
Author: ideallical
Author-email: info@ideallical.com
License: BSD
Platform: UNKNOWN
